PART_2/my_macros.vh
// Example macros
`define WIDTH 4

PART_2/rvmyth.v
// rvmyth.v - placeholder counter
module rvmyth (
    input  wire clk,
    input  wire rst,
    output reg [3:0] count
);

always @(posedge clk or posedge rst) begin
    if (rst)
        count <= 4'b0000;
    else
        count <= count + 1;
end

endmodule

testbench.v
`timescale 1ns / 1ps

// Include your macros
`include "../include/my_macros.vh"

// Testbench module
module vsdbabysoc_tb;
    reg clk;
    reg reset;
    wire [3:0] count;

    // Instantiate placeholder counter
    rvmyth uut (
        .clk(clk),
        .rst(reset),
        .count(count)
    );

    // Clock generation
    initial clk = 0;
    always #5 clk = ~clk;

    // Test sequence
    initial begin
        reset = 1;
        #10 reset = 0;
        #100 $finish;
    end

    // VCD waveform
    initial begin
        $dumpfile("/home/nagasuresh/Manali/VSDBabySoC/output/pre_synth_sim/rvmyth.vcd");

        $dumpvars(0, vsdbabysoc_tb);
    end
endmodule

rvmyth.vcd
$date
	Sun Sep 28 15:56:40 2025
$end
$version
	Icarus Verilog
$end
$timescale
	1ps
$end
$scope module vsdbabysoc_tb $end
$var wire 4 ! count [3:0] $end
$var reg 1 " clk $end
$var reg 1 # reset $end
$scope module uut $end
$var wire 1 " clk $end
$var wire 1 # rst $end
$var reg 4 $ count [3:0] $end
$upscope $end
$upscope $end
$enddefinitions $end
$comment Show the parameter values. $end
$dumpall
$end
#0
$dumpvars
b0 $
1#
0"
b0 !
$end
#5000
1"
#10000
0"
0#
#15000
b1 !
b1 $
1"
#20000
0"
#25000
b10 !
b10 $
1"
#30000
0"
#35000
b11 !
b11 $
1"
#40000
0"
#45000
b100 !
b100 $
1"
#50000
0"
#55000
b101 !
b101 $
1"
#60000
0"
#65000
b110 !
b110 $
1"
#70000
0"
#75000
b111 !
b111 $
1"
#80000
0"
#85000
b1000 !
b1000 $
1"
#90000
0"
#95000
b1001 !
b1001 $
1"
#100000
0"
#105000
b1010 !
b1010 $
1"
